{
  "type": "light",
  "colors": {
    "editor.foreground": "#050505",
    "editor.background": "#e0e0e0",
  },
  "tokenColors": [
    {
      "scope": "comment",
      "settings": {
        "fontStyle": "italic",
        "foreground": "#0967b4"
      }
    },
    {
      "scope": "comment punctuation",
      "settings": {
        "fontStyle": "italic",
        "foreground": "#0967b4"
      }
    },
    {
      "scope": "storage.modifier",
      "settings": {
        "fontStyle": "italic"
      }
    },
    {
      "scope": "keyword",
      "settings": {
        "fontStyle": "bold italic",
        "foreground": "#b10b6c"
      }
    },
    {
      "scope": "keyword.operator",
      "settings": {
        "fontStyle": "",
        "foreground": "#050505"
      }
    },
    {
      "scope": "meta.attribute",
      "settings": {
        "fontStyle": "bold italic",
        "foreground": "#b10b6c"
      }
    },
    {
      "scope": "keyword.definition",
      "settings": {
        "fontStyle": "bold italic",
        "foreground": "#b10b6c"
      }
    },
    {
      "scope": "variable.language",
      "settings": {
        "fontStyle": "italic"
      }
    },
    {
      "scope": "entity.name.type",
      "settings": {}
    },
    {
      "scope": "entity.name.trait",
      "settings": {}
    },
    {
      "scope": "entity.name.function",
      "settings": {}
    },
    {
      "scope": "variable.parameter",
      "settings": {}
    },
    {
      "scope": "meta.constant.definition entity.name.constant",
      "settings": {
        "fontStyle": "underline"
      }
    },
    {
      "scope": "meta.function.definition entity.name.function",
      "settings": {
        "fontStyle": "underline"
      }
    },
    {
      "scope": "meta.type.definition entity.name.type",
      "settings": {
        "fontStyle": "underline"
      }
    },
    {
      "scope": "meta.type.definition entity.name.trait",
      "settings": {
        "fontStyle": "underline"
      }
    },
    {
      "scope": "punctuation",
      "settings": {}
    },
    {
      "scope": "punctuation.brackets",
      "settings": {}
    },
    {
      "scope": "meta.brace",
      "settings": {
        "fontStyle": ""
      }
    },
    {
      "scope": "constant",
      "settings": {}
    },
    {
      "scope": "string",
      "settings": {
        // "fontStyle": "italic",
        "foreground": "#0b8300"
      }
    },
    {
      "scope": "string punctuation",
      "settings": {
        // "fontStyle": "italic",
        "foreground": "#0b8300"
      }
    },
    {
      "scope": "support.type.property-name.json",
      "settings": {
        "fontStyle": "italic"
      }
    },
    {
      "scope": "punctuation.support.type.property-name.begin.json",
      "settings": {
        "foreground": "#777777",
        "fontStyle": "italic"
      }
    },
    {
      "scope": "punctuation.support.type.property-name.end.json",
      "settings": {
        "foreground": "#777777",
        "fontStyle": "italic"
      }
    },
    {
      "scope": "entity.name.tag.yaml",
      "settings": {
        "fontStyle": "italic"
      }
    },
    {
      "scope": "markup.heading",
      "settings": {
        "fontStyle": "bold"
      }
    },
    {
      "scope": "markup.inline",
      "settings": {}
    },
    {
      "scope": "markup.italic",
      "settings": {
        "fontStyle": "italic"
      }
    },
    {
      "scope": "markup.bold",
      "settings": {
        "fontStyle": "bold"
      }
    },
    {
      "scope": "markup.quote",
      "settings": {
        "fontStyle": "italic"
      }
    },
    {
      "scope": "markup.raw.block",
      "settings": {}
    },
    {
      "scope": "markup.fenced_code",
      "settings": {}
    },
    {
      "scope": "fenced_code.block.language",
      "settings": {}
    }
  ]
}